arygem/__init__.py
arygem/client.py
arygem-0.1.0.dist-info/METADATA
arygem-0.1.0.dist-info/WHEEL
arygem-0.1.0.dist-info/top_level.txt
arygem-0.1.0.dist-info/RECORD
