Metadata-Version: 2.4
Name: arygem
Version: 0.1.0
Summary: A simple Python wrapper for Google Gemini AI
Home-page: https://github.com/arycodes/arygem
Author: Aryan Mishra
Classifier: Programming Language :: Python :: 3
Classifier: License :: OSI Approved :: MIT License
Classifier: Operating System :: OS Independent
Requires-Python: >=3.9
Requires-Dist: google-genai>=0.10.0
Dynamic: author
Dynamic: classifier
Dynamic: description
Dynamic: description-content-type
Dynamic: home-page
Dynamic: requires-dist
Dynamic: requires-python
Dynamic: summary
